{"nodes": [{"id": "e_ecom_ecom_frontend_app_store_products_slug_page_tsx", "label": "page.tsx", "file_type": "code", "source_file": "e:\\ecom\\ecom-frontend\\app\\(store)\\products\\[slug]\\page.tsx", "source_location": "L1"}, {"id": "page_generatestaticparams", "label": "generateStaticParams()", "file_type": "code", "source_file": "e:\\ecom\\ecom-frontend\\app\\(store)\\products\\[slug]\\page.tsx", "source_location": "L21"}, {"id": "page_generatemetadata", "label": "generateMetadata()", "file_type": "code", "source_file": "e:\\ecom\\ecom-frontend\\app\\(store)\\products\\[slug]\\page.tsx", "source_location": "L180"}], "edges": [{"source": "e_ecom_ecom_frontend_app_store_products_slug_page_tsx", "target": "cache", "relation": "imports_from", "confidence": "EXTRACTED", "source_file": "e:\\ecom\\ecom-frontend\\app\\(store)\\products\\[slug]\\page.tsx", "source_location": "L1", "weight": 1.0}, {"source": "e_ecom_ecom_frontend_app_store_products_slug_page_tsx", "target": "react", "relation": "imports_from", "confidence": "EXTRACTED", "source_file": "e:\\ecom\\ecom-frontend\\app\\(store)\\products\\[slug]\\page.tsx", "source_location": "L2", "weight": 1.0}, {"source": "e_ecom_ecom_frontend_app_store_products_slug_page_tsx", "target": "react", "relation": "imports_from", "confidence": "EXTRACTED", "source_file": "e:\\ecom\\ecom-frontend\\app\\(store)\\products\\[slug]\\page.tsx", "source_location": "L3", "weight": 1.0}, {"source": "e_ecom_ecom_frontend_app_store_products_slug_page_tsx", "target": "admin", "relation": "imports_from", "confidence": "EXTRACTED", "source_file": "e:\\ecom\\ecom-frontend\\app\\(store)\\products\\[slug]\\page.tsx", "source_location": "L4", "weight": 1.0}, {"source": "e_ecom_ecom_frontend_app_store_products_slug_page_tsx", "target": "navigation", "relation": "imports_from", "confidence": "EXTRACTED", "source_file": "e:\\ecom\\ecom-frontend\\app\\(store)\\products\\[slug]\\page.tsx", "source_location": "L5", "weight": 1.0}, {"source": "e_ecom_ecom_frontend_app_store_products_slug_page_tsx", "target": "link", "relation": "imports_from", "confidence": "EXTRACTED", "source_file": "e:\\ecom\\ecom-frontend\\app\\(store)\\products\\[slug]\\page.tsx", "source_location": "L6", "weight": 1.0}, {"source": "e_ecom_ecom_frontend_app_store_products_slug_page_tsx", "target": "utils", "relation": "imports_from", "confidence": "EXTRACTED", "source_file": "e:\\ecom\\ecom-frontend\\app\\(store)\\products\\[slug]\\page.tsx", "source_location": "L7", "weight": 1.0}, {"source": "e_ecom_ecom_frontend_app_store_products_slug_page_tsx", "target": "lucide_react", "relation": "imports_from", "confidence": "EXTRACTED", "source_file": "e:\\ecom\\ecom-frontend\\app\\(store)\\products\\[slug]\\page.tsx", "source_location": "L8", "weight": 1.0}, {"source": "e_ecom_ecom_frontend_app_store_products_slug_page_tsx", "target": "e_ecom_ecom_frontend_app_store_products_slug_productgallery", "relation": "imports_from", "confidence": "EXTRACTED", "source_file": "e:\\ecom\\ecom-frontend\\app\\(store)\\products\\[slug]\\page.tsx", "source_location": "L9", "weight": 1.0}, {"source": "e_ecom_ecom_frontend_app_store_products_slug_page_tsx", "target": "e_ecom_ecom_frontend_app_store_products_slug_variantselector", "relation": "imports_from", "confidence": "EXTRACTED", "source_file": "e:\\ecom\\ecom-frontend\\app\\(store)\\products\\[slug]\\page.tsx", "source_location": "L10", "weight": 1.0}, {"source": "e_ecom_ecom_frontend_app_store_products_slug_page_tsx", "target": "e_ecom_ecom_frontend_app_store_products_slug_addtocartbutton", "relation": "imports_from", "confidence": "EXTRACTED", "source_file": "e:\\ecom\\ecom-frontend\\app\\(store)\\products\\[slug]\\page.tsx", "source_location": "L11", "weight": 1.0}, {"source": "e_ecom_ecom_frontend_app_store_products_slug_page_tsx", "target": "e_ecom_ecom_frontend_app_store_products_slug_reviewslist", "relation": "imports_from", "confidence": "EXTRACTED", "source_file": "e:\\ecom\\ecom-frontend\\app\\(store)\\products\\[slug]\\page.tsx", "source_location": "L12", "weight": 1.0}, {"source": "e_ecom_ecom_frontend_app_store_products_slug_page_tsx", "target": "e_ecom_ecom_frontend_app_store_products_slug_reviewform", "relation": "imports_from", "confidence": "EXTRACTED", "source_file": "e:\\ecom\\ecom-frontend\\app\\(store)\\products\\[slug]\\page.tsx", "source_location": "L13", "weight": 1.0}, {"source": "e_ecom_ecom_frontend_app_store_products_slug_page_tsx", "target": "e_ecom_ecom_frontend_app_store_products_slug_recommendedproducts", "relation": "imports_from", "confidence": "EXTRACTED", "source_file": "e:\\ecom\\ecom-frontend\\app\\(store)\\products\\[slug]\\page.tsx", "source_location": "L14", "weight": 1.0}, {"source": "e_ecom_ecom_frontend_app_store_products_slug_page_tsx", "target": "e_ecom_ecom_frontend_app_store_products_slug_productoffers", "relation": "imports_from", "confidence": "EXTRACTED", "source_file": "e:\\ecom\\ecom-frontend\\app\\(store)\\products\\[slug]\\page.tsx", "source_location": "L15", "weight": 1.0}, {"source": "e_ecom_ecom_frontend_app_store_products_slug_page_tsx", "target": "page_generatestaticparams", "relation": "contains", "confidence": "EXTRACTED", "source_file": "e:\\ecom\\ecom-frontend\\app\\(store)\\products\\[slug]\\page.tsx", "source_location": "L21", "weight": 1.0}, {"source": "e_ecom_ecom_frontend_app_store_products_slug_page_tsx", "target": "page_generatemetadata", "relation": "contains", "confidence": "EXTRACTED", "source_file": "e:\\ecom\\ecom-frontend\\app\\(store)\\products\\[slug]\\page.tsx", "source_location": "L180", "weight": 1.0}]}