{"nodes": [{"id": "e_ecom_ecom_frontend_app_store_account_orders_page_tsx", "label": "page.tsx", "file_type": "code", "source_file": "e:\\ecom\\ecom-frontend\\app\\(store)\\account\\orders\\page.tsx", "source_location": "L1"}], "edges": [{"source": "e_ecom_ecom_frontend_app_store_account_orders_page_tsx", "target": "user_auth", "relation": "imports_from", "confidence": "EXTRACTED", "source_file": "e:\\ecom\\ecom-frontend\\app\\(store)\\account\\orders\\page.tsx", "source_location": "L1", "weight": 1.0}, {"source": "e_ecom_ecom_frontend_app_store_account_orders_page_tsx", "target": "admin", "relation": "imports_from", "confidence": "EXTRACTED", "source_file": "e:\\ecom\\ecom-frontend\\app\\(store)\\account\\orders\\page.tsx", "source_location": "L2", "weight": 1.0}, {"source": "e_ecom_ecom_frontend_app_store_account_orders_page_tsx", "target": "link", "relation": "imports_from", "confidence": "EXTRACTED", "source_file": "e:\\ecom\\ecom-frontend\\app\\(store)\\account\\orders\\page.tsx", "source_location": "L3", "weight": 1.0}, {"source": "e_ecom_ecom_frontend_app_store_account_orders_page_tsx", "target": "utils", "relation": "imports_from", "confidence": "EXTRACTED", "source_file": "e:\\ecom\\ecom-frontend\\app\\(store)\\account\\orders\\page.tsx", "source_location": "L4", "weight": 1.0}, {"source": "e_ecom_ecom_frontend_app_store_account_orders_page_tsx", "target": "lucide_react", "relation": "imports_from", "confidence": "EXTRACTED", "source_file": "e:\\ecom\\ecom-frontend\\app\\(store)\\account\\orders\\page.tsx", "source_location": "L5", "weight": 1.0}]}