{"nodes": [{"id": "e_ecom_ecom_backend_src_middleware_auth_ts", "label": "auth.ts", "file_type": "code", "source_file": "e:\\ecom\\ecom-backend\\src\\middleware\\auth.ts", "source_location": "L1"}, {"id": "auth_requireauth", "label": "requireAuth()", "file_type": "code", "source_file": "e:\\ecom\\ecom-backend\\src\\middleware\\auth.ts", "source_location": "L8"}, {"id": "auth_requireadmin", "label": "requireAdmin()", "file_type": "code", "source_file": "e:\\ecom\\ecom-backend\\src\\middleware\\auth.ts", "source_location": "L19"}], "edges": [{"source": "e_ecom_ecom_backend_src_middleware_auth_ts", "target": "express", "relation": "imports_from", "confidence": "EXTRACTED", "source_file": "e:\\ecom\\ecom-backend\\src\\middleware\\auth.ts", "source_location": "L1", "weight": 1.0}, {"source": "e_ecom_ecom_backend_src_middleware_auth_ts", "target": "e_ecom_ecom_backend_src_middleware_lib_supabase", "relation": "imports_from", "confidence": "EXTRACTED", "source_file": "e:\\ecom\\ecom-backend\\src\\middleware\\auth.ts", "source_location": "L2", "weight": 1.0}, {"source": "e_ecom_ecom_backend_src_middleware_auth_ts", "target": "auth_requireauth", "relation": "contains", "confidence": "EXTRACTED", "source_file": "e:\\ecom\\ecom-backend\\src\\middleware\\auth.ts", "source_location": "L8", "weight": 1.0}, {"source": "e_ecom_ecom_backend_src_middleware_auth_ts", "target": "auth_requireadmin", "relation": "contains", "confidence": "EXTRACTED", "source_file": "e:\\ecom\\ecom-backend\\src\\middleware\\auth.ts", "source_location": "L19", "weight": 1.0}]}